{"id": 11252, "slug": "countess-dracula", "title": "Countess Dracula", "year": 1971, "rating": 5.9, "popularity": 5000, "duration_min": 93, "poster_url": "https://bestsimilar.com/img/movie/thumb/09/11252.jpg", "genres": ["Horror"], "country": ["UK"], "story": "Based on the story of Elisabeth Bathory, the 18th century Countess who indulged herself in an orgy of murder and vampirism before before being walled up in her room by the authorities. The ageing Countess Dracula discovers that the blood of young virgins has a restorative effect on her celebrated beauty. Years later, she becomes engaged to a handsome young Hussar and is forced to repeat vile atrocities with ever-increasing regularity to hold off old age.", "themes": ["Dracula", "Sexy", "Gothic horror", "Eternal youth", "Supernatural", "Gothic", "17th century", "Serial killer", "Humiliation", "Medieval times", "Lesbian", "Slasher"], "features": {"pacing": 0.333, "tone_register": -0.333, "ending_warmth": 0.0, "emotional_intensity": 0.0, "complexity": 0.0, "scope": 0.0, "realism": 0.667, "darkness": 0.333, "thematic_weight": 0.0, "character_focus": 0.0, "moral_clarity": 0.0, "structure": 0.0}, "similar_ids": [26254, 24609, 21936, 37089, 34852, 17690, 12456, 12450, 49078, 34647, 37238, 34878, 34842, 1025, 36917, 26255, 37416, 27043, 32586, 19571, 24192, 12077, 33753, 33490, 19411, 33617, 11474, 19827, 11435, 25757]}