{"id": 12250, "slug": "do-the-right-thing", "title": "Do the Right Thing", "year": 1989, "rating": 7.9, "popularity": 123000, "duration_min": 120, "poster_url": "https://bestsimilar.com/img/movie/thumb/54/12250.jpg", "genres": ["Comedy", "Drama"], "country": ["USA"], "story": "On the hottest day of the year on a street in the Bedford-Stuyvesant section of Brooklyn, everyone's hate and bigotry smolders and builds until it explodes into violence.", "themes": ["Heat wave", "Hood", "Racism", "Pizzeria", "Culture clash", "Hip hop", "Police brutality", "Pizza", "Riot", "Radio station", "Urban", "Gangster"], "features": {"pacing": 0.333, "tone_register": 0.333, "ending_warmth": 0.0, "emotional_intensity": 0.333, "complexity": 0.333, "scope": 0.0, "realism": -0.333, "darkness": 0.333, "thematic_weight": 0.333, "character_focus": 0.0, "moral_clarity": 0.0, "structure": 0.0}, "similar_ids": [21965, 9897, 10943, 20009, 14712, 14524, 9032, 14852, 38436, 17851, 22340, 23341, 9033, 28745, 12527, 14463, 33992, 20424, 14137, 35673, 13778, 22972, 61208, 5567, 15372, 21015, 61211, 23118, 22316, 15661]}