{"id": 13739, "slug": "freddy-vs-jason", "title": "Freddy vs. Jason", "year": 2003, "rating": 5.8, "popularity": 135000, "duration_min": 97, "poster_url": "https://bestsimilar.com/img/movie/thumb/1e/13739.jpg", "genres": ["Horror"], "country": ["Canada", "USA"], "story": "Evil dream-demon Freddy Krueger devises a plan to manipulate the unstoppable Jason Vorhees into hacking up the teenagers of Elm Street in an effort to make people remember the name Freddy Krueger, thus freeing him from limbo.", "themes": ["Serial killer", "Slasher", "Scary", "Blood", "Violence", "Brutal", "Masked man", "Gory", "Monster versus monster", "Male victim", "Homicidal maniac", "Boyfriend girlfriend relationship"], "features": {"pacing": 0.0, "tone_register": 0.0, "ending_warmth": 0.0, "emotional_intensity": 0.0, "complexity": 0.0, "scope": -0.333, "realism": 0.667, "darkness": 1.0, "thematic_weight": 0.0, "character_focus": 0.0, "moral_clarity": 0.0, "structure": 0.0}, "similar_ids": [13786, 16122, 13782, 23922, 19287, 14663, 19286, 19285, 19168, 19289, 19284, 13780, 23923, 14667, 13740, 13784, 25871, 19288, 13787, 16154, 16123, 12984, 14659, 22015, 22731, 16155, 14660, 14666, 26830, 14824]}