{"id": 14701, "slug": "the-hand-that-rocks-the-cradle", "title": "The Hand That Rocks the Cradle", "year": 1992, "rating": 6.7, "popularity": 55000, "duration_min": 110, "poster_url": "https://bestsimilar.com/img/movie/thumb/fe/14701.jpg", "genres": ["Drama", "Thriller"], "country": ["USA"], "story": "A suburban family chooses seemingly sweet Peyton Flanders as their newborn's nanny. Only much later does the infant's mother, Claire Bartel, realize Peyton's true intentions -- to destroy Claire and replace her in the family. The nail-biting suspense builds quickly in this chilling psychological thriller about deception and bitter revenge.", "themes": ["Obsession", "Suspenseful", "Home invasion", "Nanny", "Suicide", "Vengeance", "Sexual abuse", "Malice", "Husband wife relationship", "Manipulation", "Sexualized violence", "Pregnancy"], "features": {"pacing": 0.333, "tone_register": -0.333, "ending_warmth": 0.0, "emotional_intensity": 0.0, "complexity": 0.333, "scope": 0.0, "realism": 0.0, "darkness": 0.667, "thematic_weight": 0.0, "character_focus": 0.0, "moral_clarity": 0.0, "structure": 0.0}, "similar_ids": [23601, 67209, 18470, 13046, 22603, 19952, 13255, 20419, 11429, 15476, 21586, 26805, 17863, 22604, 14309, 22743, 6416, 13225, 13384, 22005, 20468, 23638, 19149, 22762, 10735, 12076, 24839, 64797, 10308, 14550]}