{"id": 15037, "slug": "john-wick", "title": "John Wick", "year": 2014, "rating": 7.5, "popularity": 818000, "duration_min": 101, "poster_url": "https://bestsimilar.com/img/movie/thumb/26/15037.jpg", "genres": ["Action", "Crime", "Thriller"], "country": ["USA"], "story": "Ex-hitman John Wick comes out of retirement to track down the gangsters that took everything from him.", "themes": ["Hitman", "Vengeance", "Revenge", "One man army", "Assassin", "Vigilante", "Shooting", "Gunfight", "Gunslinger", "Widower", "Crime boss", "Violence"], "features": {"pacing": 1.0, "tone_register": -0.333, "ending_warmth": 0.0, "emotional_intensity": 0.0, "complexity": 0.0, "scope": 0.0, "realism": 0.0, "darkness": 1.0, "thematic_weight": -0.333, "character_focus": 0.0, "moral_clarity": 0.0, "structure": 0.0}, "similar_ids": [38395, 64485, 71019, 79450, 19393, 71071, 26266, 38399, 18171, 23667, 21432, 9808, 61036, 26616, 7845, 24368, 28022, 25343, 20848, 16591, 17920, 65037, 11301, 15141, 26981, 57457, 8071, 8718, 57900, 27765]}