{"id": 16508, "slug": "keane", "title": "Keane", "year": 2004, "rating": 6.8, "popularity": 6000, "duration_min": 100, "poster_url": "https://bestsimilar.com/img/movie/thumb/c9/16508.jpg", "genres": ["Drama", "Mystery", "Thriller"], "country": ["USA"], "story": "A mentally ill man searches New York for his missing eight year old daughter. He recreates her steps each day hoping for some clue to her disappearance, until he meets and befriend a woman with a daughter the same age. Could she help him with the missing piece of the puzzle?", "themes": ["Kidnapping", "Mental illness", "Missing child", "Little girl", "Sincere", "Schizophrenia", "Missing person", "Self destructing", "Illness", "Suspense", "Hotel", "Suicide"], "features": {"pacing": 0.333, "tone_register": -0.333, "ending_warmth": 0.0, "emotional_intensity": 0.333, "complexity": 0.333, "scope": 0.0, "realism": 0.0, "darkness": 0.0, "thematic_weight": 0.0, "character_focus": 0.0, "moral_clarity": 0.0, "structure": 0.333}, "similar_ids": [10922, 37639, 20778, 26691, 14270, 69720, 10894, 13544, 10129, 22177, 3729, 7994, 74176, 23662, 25725, 23053, 25553, 70690, 7114, 36391, 5428, 10925, 26760, 28140, 5743, 9503, 27693, 18221, 13649, 25438]}