{"id": 18625, "slug": "moon", "title": "Moon", "year": 2009, "rating": 7.8, "popularity": 392000, "duration_min": 97, "poster_url": "https://bestsimilar.com/img/movie/thumb/4d/18625.jpg", "genres": ["Drama", "Mystery", "Sci-Fi"], "country": ["UK", "USA"], "story": "With only three weeks left in his three year contract, Sam Bell is getting anxious to finally return to Earth. He is the only occupant of a Moon-based manufacturing facility along with his computer and assistant, GERTY. When he has an accident however, he wakens to find that he is not alone.", "themes": ["Isolation", "Moon", "Psychological", "Loneliness", "Space travel", "Philosophical", "Outer space", "Future", "Distopia", "Dystopia", "Mission", "Nervous breakdown"], "features": {"pacing": 0.667, "tone_register": 0.0, "ending_warmth": -0.333, "emotional_intensity": 0.0, "complexity": 1.0, "scope": 0.0, "realism": 0.667, "darkness": 0.0, "thematic_weight": 0.333, "character_focus": 0.0, "moral_clarity": 0.0, "structure": 0.0}, "similar_ids": [27702, 7283, 12958, 3215, 27091, 7676, 22899, 23485, 4807, 26725, 19989, 13977, 64842, 65555, 38412, 26313, 17902, 24586, 20305, 26207, 19388, 22867, 7886, 18213, 8133, 62275, 253, 25406, 13667, 26210]}