{"id": 22964, "slug": "sorry-haters", "title": "Sorry, Haters", "year": 2005, "rating": 6.2, "popularity": 2000, "duration_min": 83, "poster_url": "https://bestsimilar.com/img/movie/thumb/09/22964.jpg", "genres": ["Drama", "Thriller"], "country": ["USA"], "story": "Against the anxieties and fears of post-9/11 America, an Arab cab driver picks up a troubled professional woman with unexpected results.", "themes": ["Terrorism", "Terrorist", "Culture clash", "New york", "War on terror", "Suspenseful", "Disturbing", "Psychological", "Illness", "9/11", "Driver", "Mental illness"], "features": {"pacing": 0.333, "tone_register": -0.333, "ending_warmth": 0.0, "emotional_intensity": 0.0, "complexity": 0.0, "scope": 0.333, "realism": -0.333, "darkness": 0.333, "thematic_weight": 0.0, "character_focus": 0.0, "moral_clarity": 0.0, "structure": 0.0}, "similar_ids": [37674, 11403, 21227, 5995, 13488, 19718, 36237, 4331, 32053, 7617, 5971, 13225, 14701, 14753, 74793, 10161, 19173, 10308, 16688, 11347, 13255, 9725, 36003, 16953, 23601, 13490, 12088, 13352, 13485, 12542]}