{"id": 27336, "slug": "bad-grandpa", "title": "Jackass Presents: Bad Grandpa", "year": 2013, "rating": 6.5, "popularity": 100000, "duration_min": 92, "poster_url": "https://bestsimilar.com/img/movie/thumb/40/27336.jpg", "genres": ["Comedy"], "country": ["USA"], "story": "86-year-old Irving Zisman is on a journey across America with the most unlikely companion: his 8 year-old grandson, Billy.", "themes": ["Road trip", "On the road", "Humorous", "Male nudity", "Black comedy", "North carolina", "Jackass", "Dirty old man", "Hilarious", "Adult humor", "Old man", "Little boy"], "features": {"pacing": 0.0, "tone_register": 0.5, "ending_warmth": 0.0, "emotional_intensity": 0.0, "complexity": 0.0, "scope": 0.667, "realism": 0.333, "darkness": 0.333, "thematic_weight": -0.667, "character_focus": 0.0, "moral_clarity": 0.0, "structure": 0.0}, "similar_ids": [37954, 65122, 9817, 65112, 26568, 4497, 67419, 18155, 11841, 5322, 14717, 16275, 27730, 24964, 10071, 23246, 21472, 56455, 19649, 16174, 94241, 883, 22789, 9186, 14716, 12193, 26189, 26261, 131, 62124]}