{"id": 34984, "slug": "the-giant-spider-invasion", "title": "The Giant Spider Invasion", "year": 1975, "rating": 3.3, "popularity": 5000, "duration_min": 80, "poster_url": "https://bestsimilar.com/img/movie/thumb/a8/34984.jpg", "genres": ["Horror", "Sci-Fi"], "country": ["USA", "Japan"], "story": "A black hole hits North Wisconsin and opens a door to other dimensions. Giant 15 meter spiders emerge from it, who have an appetite for human flesh! Dr. Jenny Langer and Dr. Vance from the NASA try to save the world.", "themes": ["Small town", "Giant spider", "Spider", "Kaiju", "Scary", "Evil alien", "Monster", "Cobweb", "Crystal", "Killer animal", "Animal attack", "Captivating"], "features": {"pacing": 0.0, "tone_register": -0.333, "ending_warmth": 0.0, "emotional_intensity": 0.0, "complexity": 0.0, "scope": -0.333, "realism": 0.667, "darkness": 0.333, "thematic_weight": 0.0, "character_focus": 0.0, "moral_clarity": 0.0, "structure": 0.0}, "similar_ids": [34974, 30611, 101664, 32658, 12693, 23058, 37307, 34987, 34928, 15771, 22654, 875, 11375, 16974, 88853, 32012, 35732, 23059, 33439, 24401, 9094, 18681, 2989, 25445, 36278, 19131, 21296, 34930, 22254, 24403]}