{"id": 41649, "slug": "the-last-band-in-lebanon", "title": "The Last Band in Lebanon", "year": 2016, "rating": 6.6, "popularity": 322, "duration_min": 99, "poster_url": "https://bestsimilar.com/img/movie/thumb/9c/41649.jpg", "genres": ["Comedy"], "country": ["Israel"], "story": "A comedy about three military band reservists who wake to discover that the Israeli army has withdrawn from Lebanon and left them behind.", "themes": ["Lebanon", "Israel", "Friendship", "Rock band", "Drug smuggling", "Fish out of water", "Buddy comedy", "Misadventure", "Road movie", "Uplifting", "Suspenseful", "Anti war"], "features": {"pacing": 0.333, "tone_register": 1.0, "ending_warmth": 0.333, "emotional_intensity": -0.333, "complexity": 0.0, "scope": 0.333, "realism": 0.0, "darkness": -0.333, "thematic_weight": 0.0, "character_focus": 0.0, "moral_clarity": 0.333, "structure": 0.0}, "similar_ids": [107254, 109464, 102745, 102910, 48053, 53802, 48776, 109602, 109758, 33792, 101632, 94914, 47413, 80143, 32802, 106916, 106668, 44880, 98843, 86458, 55952, 43772, 103322, 105376, 99464, 54760, 107377, 97798, 44371, 94636]}