{"id": 44321, "slug": "jonis-promise", "title": "Joni's Promise", "year": 2005, "rating": 7.6, "popularity": 2000, "duration_min": 83, "poster_url": "https://bestsimilar.com/img/movie/thumb/1a/44321.jpg", "genres": ["Adventure", "Comedy", "Drama", "Romance"], "country": ["Indonesia"], "story": "A film delivery man promises a beautiful young woman to deliver a film reel on time to a movie theater. But the the whole city seems to conspire against him.", "themes": ["Indonesia", "Road movie", "Passion", "2000s", "Movie business", "Dedication", "Commitment", "Gay", "Chase", "City", "Robbery", "Debt collector"], "features": {"pacing": 0.333, "tone_register": 0.667, "ending_warmth": 0.0, "emotional_intensity": 0.0, "complexity": 0.0, "scope": 0.0, "realism": 0.0, "darkness": 0.333, "thematic_weight": 0.0, "character_focus": 0.0, "moral_clarity": 0.0, "structure": 0.0}, "similar_ids": [44756, 2752, 12851, 91830, 19796, 18312, 21536, 15200, 59346, 8672, 18935, 53420, 9420, 41644, 22281, 30839, 6695, 12688, 10700, 102404, 8685, 12731, 38603, 57521, 18853, 75783, 31058, 101920, 67341, 107427]}