{"id": 64703, "slug": "texas-46", "title": "Texas '46", "year": 2002, "rating": 5.9, "popularity": 241, "duration_min": 96, "poster_url": "https://bestsimilar.com/img/movie/thumb/fc/64703.jpg", "genres": ["Drama", "History", "War"], "country": ["USA", "Italy"], "story": "Based on a true story its the untold story of Italian World War II POW\"S in Jan 1946. Luca Zingaretti stars as one of over 50,000 Italian Prisoners of War detained at POW camps in the U.S. Roy Schneider stars as Colonel Gartner, the Commander of the camp. Things take a turn for the worse when Manin is brought back from his most recent escape by a patrol force, only to realize that the camp has been evacuated while he was gone. Gartner is forced to keep Manin at the camp until another patrol force can come pick him up. However, no one ever comes. The phone lines get cut, and the two men realize they are completely isolated from the outside world. It is up to each man now to escape the camp.An untold and rarely known fact of US held Italian POW\"S", "themes": ["Fascism", "World war two", "Military", "Military life", "Rough", "Genocide", "Captivity", "Realistic", "Holocaust", "Bleak", "Battles", "Captivating"], "features": {"pacing": 0.333, "tone_register": -0.333, "ending_warmth": -0.333, "emotional_intensity": 0.0, "complexity": 0.0, "scope": 0.333, "realism": -0.333, "darkness": 0.333, "thematic_weight": 0.0, "character_focus": 0.0, "moral_clarity": 0.0, "structure": 0.0}, "similar_ids": [15620, 21053, 85432, 10059, 35578, 22411, 33109, 31722, 36138, 12656, 3979, 15985, 12906, 34387, 32479, 63314, 72825, 64919, 2010, 749, 31701, 62086, 25030, 8563, 8338, 3757, 33009, 33527, 3756, 4959]}