{"id": 67306, "slug": "ricky-gervais-humanity", "title": "Ricky Gervais: Humanity", "year": 2018, "rating": 8.0, "popularity": 25000, "duration_min": 79, "poster_url": "https://bestsimilar.com/img/movie/thumb/b3/67306.jpg", "genres": ["Comedy"], "country": ["UK"], "story": "In his first special in seven years, Ricky Gervais slings his trademark snark at celebrity, mortality and a society that takes everything personally.", "themes": ["Comedian", "Stand up comedian", "Funny", "Profanity", "Stand up comedy", "Light", "Humorous", "Witty", "Fun", "Performance", "Stand up special", "Loud"], "features": {"pacing": 0.0, "tone_register": 1.0, "ending_warmth": 0.0, "emotional_intensity": 0.0, "complexity": 0.0, "scope": 0.0, "realism": 0.333, "darkness": 0.0, "thematic_weight": -0.333, "character_focus": 0.0, "moral_clarity": -0.333, "structure": 0.0}, "similar_ids": [69346, 1844, 79326, 68021, 68035, 55023, 68036, 64905, 69767, 67043, 66541, 74676, 68039, 67673, 110706, 68023, 59831, 68033, 76634, 103564, 69186, 1306, 107531, 99369, 67390, 77502, 77682, 102774, 51153, 48554]}