{"id": 67950, "slug": "havel", "title": "Havel", "year": 2020, "rating": 6.3, "popularity": 551, "duration_min": 104, "poster_url": "https://bestsimilar.com/img/movie/thumb/bb/67950.jpg", "genres": ["Biography", "Drama", "History"], "country": ["Czech Republic"], "story": "It's the summer of '68 and the young Czech playwright Vaclav Havel is enjoying the heady atmosphere of new- found freedom as the iron grip of Soviet repression gradually loosens throughout Central Europe. In Havel's Prague, politics are as exciting as theatre, sex, drugs and rock 'n' roll. Havel, though, is a comfortable and acclaimed playwright, and he's determined to avoid conflict that might upset his world. He resists confrontation with the political authorities - led by the celebrated politician Alexander Dubcek - and he tries to carry out his romantic escapades without undermining his marriage to his beloved Olga. Havel's fling with freedom comes to an abrupt and violent end when Soviet Russia invades Czechoslovakia. When Havel refuses to sign a regime-sponsored document approving of the Russian occupation, the government removes him from his theater and from his prestigious position at the pinnacle of Czech cultural life. The now-banned author retreats from the limelight to his...", "themes": ["Playwright", "Czech history", "Conscience", "Lifestyle change", "Political activist", "Fight", "Friendship between men", "Jail", "Heavy smoker", "Biopic", "Dog", "Prison"], "features": {"pacing": 0.0, "tone_register": -0.667, "ending_warmth": 0.0, "emotional_intensity": 0.0, "complexity": 0.0, "scope": 0.0, "realism": -0.333, "darkness": 0.0, "thematic_weight": 0.0, "character_focus": 0.333, "moral_clarity": 0.0, "structure": 0.0}, "similar_ids": [90535, 66509, 59352, 4474, 11606, 43243, 39581, 10445, 56542, 12686, 17732, 13938, 18392, 11432, 98660, 56238, 78843, 10312, 21956, 40823, 17695, 21177, 17851, 19354, 17000, 14302, 13829, 11515, 40975, 33131]}