{"id": 7437, "slug": "22-jump-street", "title": "22 Jump Street", "year": 2014, "rating": 7.0, "popularity": 436000, "duration_min": 112, "poster_url": "https://bestsimilar.com/img/movie/thumb/b5/7437.jpg", "genres": ["Action", "Comedy", "Crime", "Mystery"], "country": ["USA"], "story": "After making their way through high school (twice), big changes are in store for officers Schmidt and Jenko when they go deep undercover at a local college. But when Jenko meets a kindred spirit on the football team, and Schmidt infiltrates the bohemian art major scene, they begin to question their partnership. Now they don't have to just crack the case - they have to figure out if they can have a mature relationship. If these two overgrown adolescents can grow from freshmen into real men, college might be the best thing that ever happened to them.", "themes": ["College", "Teens", "Hilarious", "Undercover cop", "Action comedy", "Buddy comedy", "Exciting", "Funny", "Undercover", "Profanity", "American football", "Fraternity"], "features": {"pacing": 0.667, "tone_register": 1.0, "ending_warmth": 0.0, "emotional_intensity": 0.0, "complexity": 0.0, "scope": 0.0, "realism": 0.0, "darkness": 0.0, "thematic_weight": -0.667, "character_focus": 0.0, "moral_clarity": 0.0, "structure": 0.0}, "similar_ids": [26325, 65789, 23196, 38339, 14440, 27210, 15311, 8920, 19860, 3405, 26670, 27764, 6112, 38916, 40744, 41506, 7722, 21708, 27078, 7092, 72330, 24478, 26261, 23494, 16653, 1603, 12423, 26540, 11208, 16548]}