{"id": 79731, "slug": "to-leslie", "title": "To Leslie", "year": 2022, "rating": 7.1, "popularity": 19000, "duration_min": 119, "poster_url": "https://bestsimilar.com/img/movie/thumb/ba/79731.jpg", "genres": ["Drama"], "country": ["USA"], "story": "A West Texas single mother wins the lottery and squanders it just as fast, leaving behind a world of heartbreak. Years later, with her charm running out and nowhere to go, she fights to rebuild her life and find redemption.", "themes": ["Addiction", "Lottery", "Homeless woman", "Redemption", "Alcohol abuse", "Son", "Lottery winner", "Based on true story", "Cerebral", "Alcoholism", "70s", "Strong female lead"], "features": {"pacing": 0.0, "tone_register": -0.333, "ending_warmth": 0.333, "emotional_intensity": -0.333, "complexity": 0.667, "scope": 0.0, "realism": -0.667, "darkness": 0.0, "thematic_weight": 0.333, "character_focus": 0.0, "moral_clarity": 0.333, "structure": 0.0}, "similar_ids": [36513, 16189, 66077, 65482, 18929, 85152, 11715, 4337, 99494, 43484, 24000, 1721, 68984, 57055, 15992, 10920, 81568, 57680, 52183, 85982, 57147, 9996, 65138, 39901, 15785, 13687, 42305, 2034, 38618, 18345]}