{"id": 9125, "slug": "beach-red", "title": "Beach Red", "year": 1967, "rating": 6.2, "popularity": 2000, "duration_min": 105, "poster_url": "https://bestsimilar.com/img/movie/thumb/8f/9125.jpg", "genres": ["Drama", "War"], "country": ["USA"], "story": "American troops storm ashore on a Japanese-held island and push inland while their enemies plan a counterattack in this look at warfare. Soldiers on both sides are haunted by memories of home and the horrifying, sickening images they find in combat.", "themes": ["World war two", "War", "Island", "Military", "World war", "Combat", "Japanese soldier", "Marine", "Beach", "Pacific island", "Based on book", "Rough"], "features": {"pacing": 0.0, "tone_register": -0.333, "ending_warmth": -0.333, "emotional_intensity": 0.0, "complexity": 0.0, "scope": 0.333, "realism": -0.333, "darkness": 0.0, "thematic_weight": 0.0, "character_focus": 0.0, "moral_clarity": 0.0, "structure": 0.0}, "similar_ids": [646, 24197, 34054, 33109, 14945, 25703, 32156, 832, 24242, 9983, 35582, 79086, 8185, 25351, 8563, 21656, 9105, 20998, 16684, 16774, 25548, 33074, 14436, 14684, 7511, 13858, 9387, 13191, 4171, 51800]}