{"id": 1233, "slug": "the-office", "title": "The Office", "year": 2005, "rating": 9.0, "popularity": 819000, "duration_min": 22, "poster_url": "https://bestsimilar.com/img/movie/thumb/a3/1233.jpg", "genres": ["Comedy"], "country": ["USA"], "story": "The everyday lives of office employees in the Scranton, Pennsylvania branch of the fictional Dunder Mifflin Paper Company.", "themes": ["Workplace", "Job", "Office", "Satire", "Employer employee relationship", "Mockumentary", "Salesman", "Office romance", "Power relations", "Realistic", "Bully", "Prank"], "features": {"pacing": 0.0, "tone_register": 0.714, "ending_warmth": 0.333, "emotional_intensity": 0.0, "complexity": 0.0, "scope": 0.0, "realism": -0.333, "darkness": 0.0, "thematic_weight": -0.333, "character_focus": 0.0, "moral_clarity": 0.0, "structure": 0.0}, "similar_ids": [26681, 30449, 29840, 8415, 30442, 8662, 26561, 16022, 61092, 30523, 62814, 30454, 5359, 30505, 67369, 30420, 59213, 30506, 67575, 62008, 19620, 90456, 30165, 30160, 93664, 26562, 85406, 3822, 68832, 98218]}